pypxl/__init__.py
pypxl/client.py
pypxl/errors.py
pypxl/pxl_object.py
pypxl-0.2.4.dist-info/LICENSE
pypxl-0.2.4.dist-info/METADATA
pypxl-0.2.4.dist-info/WHEEL
pypxl-0.2.4.dist-info/top_level.txt
pypxl-0.2.4.dist-info/RECORD
